Workbook

Sheet Sintesi
A1: VENERE — Sintesi del modello finanziario
A2: Base case regime AMBULATORIO, numeri illustrativi da validare in DD. Il file RICALCOLA all'apertura in Excel o Google Sheets.
A4: Numeri chiave (base case)
A5: MOIC per ambulatorio convertito | B5: =Unit_Economics!B21
A6: Capitale investito per centro | B6: =Unit_Economics!B11
A7: EBITDA a regime per centro | B7: =Unit_Economics!B15
A8: Seed — totale impieghi (vs €500k) | B8: =Seed_500k!B8
A9: Seed — residuo dopo il pilota (LOI + WC) | B9: =Seed_500k!B12
A10: EBITDA gruppo Anno 5 | B10: =Gruppo_Returns!F8
A11: Enterprise Value all'exit (Anno 5) | B11: =Gruppo_Returns!B12
A12: MOIC investitore seed | B12: =Gruppo_Returns!E16
A13: Valore fondatori all'exit | B13: =Gruppo_Returns!D19
A15: Come si legge: celle BLU (foglio Assunzioni) = leve modificabili · VERDE = link tra fogli · NERO = formula.
A16: Fogli: Assunzioni · Unit_Economics · Seed_500k · Gruppo_Returns.

Sheet Assunzioni
A1: VENERE — Modello finanziario · Assunzioni (celle blu = leve modificabili)
A2: Numeri illustrativi, base case (regime AMBULATORIO). Da validare in DD. Fonti: annunci idealista/immobiliare, benchmark medspa USA, deck Venere v7.
A4: UNIT ECONOMICS — un centro convertito
A5: Ricavi centro all'acquisto | B5: 650000 | C5: €/anno | D5: centro estetico affermato con footfall reale
A6: Margine EBITDA all'acquisto | B6: 0.15 | D6: tipico centro estetico
A7: Prezzo d'acquisto (cessione attività) | B7: 350000 | D7: circa 3,5x EBITDA normalizzato (grande centro)
A8: Capex di conversione in ambulatorio | B8: 350000 | D8: AMBULATORIO: locali distinti, impianti, autorizzazione, sterilizzazione, device (range 250-450k)
A9: Ricavi a regime (medicalizzato, 24m) | B9: 1200000 | C9: €/anno | D9: beauty + medicina estetica in ambulatorio, su base clienti
A10: Margine EBITDA a regime | B10: 0.25 | D10: medspa maturi 20-28%; prudente 25%
A11: Multiplo di uscita (EBITDA) | B11: 8 | D11: healthcare-services 7-10x; upside AI-platform
A12: Fattore di maturità dei ricavi (blended) | B12: 0.8 | D12: sedi non tutte a regime nell'anno
A14: ROLLOUT — centri medicalizzati cumulati per anno
A15: Anno 1 | B15: 1 | D15: Anno 1 = seed (1 ambulatorio pilota); da Anno 2 la scala
A16: Anno 2 | B16: 5
A17: Anno 3 | B17: 10
A18: Anno 4 | B18: 16
A19: Anno 5 | B19: 24
A21: COSTO PIATTAFORMA CENTRALE (HQ, management, AI, brand) — €/anno
A22: Anno 1 | B22: 300000
A23: Anno 2 | B23: 600000
A24: Anno 3 | B24: 1000000
A25: Anno 4 | B25: 1400000
A26: Anno 5 | B26: 1800000
A28: FUNDING — le due raccolte
A29: Seed (l'ask di oggi) | B29: 700000 | D29: seed-pilota: 1 ambulatorio pilota completo + 3 LOI blindate
A30: Seed — post-money | B30: 4500000 | D30: post-money indicativo (~15% ceduto); floor 3,5M (20%)
A31: Round di scala | B31: 4000000 | D31: a modello provato (range 3-5M); converte i 3 + cluster
A32: Round di scala — post-money | B32: 15000000 | D32: valutazione ipotizzata
A33: Pool ESOP (management, incl. COO) | B33: 0.12 | D33: creato al round di scala
A35: SEED — sotto-assunzioni (1 ambulatorio pilota + pipeline LOI)
A36: Cash al closing centro pilota | B36: 200000 | D36: cash al closing pilota (con rollover del venditore)
A37: Capex conversione ambulatorio pilota (lean) | B37: 350000 | D37: capex pieno sul pilota (con €700k te lo puoi permettere)
A38: N ambulatori convertiti nel seed | B38: 1 | D38: il pilota; gli altri 2 in Series A
A39: Acconti/opzioni su 2 LOI aggiuntive | B39: 20000 | D39: blindare la pipeline per la Series A

Sheet Unit_Economics
A1: Unit economics — un centro estetico convertito in ambulatorio
A3: All'acquisto (centro estetico)
A4: Ricavi | B4: =Assunzioni!B5
A5: EBITDA | B5: =Assunzioni!B5*Assunzioni!B6
A6: Prezzo d'acquisto | B6: =Assunzioni!B7
A7: Multiplo implicito d'acquisto | B7: =B6/B5 | D7: a quanto stai comprando l'EBITDA
A9: Conversione in ambulatorio
A10: Capex di conversione in ambulatorio | B10: =Assunzioni!B8
A11: Capitale investito totale | B11: =B6+B10
A13: A regime (24 mesi, ambulatorio)
A14: Ricavi a regime | B14: =Assunzioni!B9
A15: EBITDA a regime | B15: =Assunzioni!B9*Assunzioni!B10
A16: Uplift EBITDA vs acquisto | B16: =B15-B5
A18: Creazione di valore ed exit
A19: Valore a regime (EBITDA x multiplo) | B19: =B15*Assunzioni!B11
A20: Valore creato (netto del capitale investito) | B20: =B19-B11
A21: MOIC per centro (valore / capitale investito) | B21: =B19/B11
A23: Doppio arbitraggio: compri a sconto (multiplo basso) + converti in ambulatorio (EBITDA su, re-rating a multiplo medico). Capex piu' alto dello studio medico: e' la barra che fa da fossato.

Sheet Seed_500k
A1: Seed €500k — use of funds (cosa compra davvero, regime ambulatorio)
A3: Impieghi
A4: Cash al closing centro pilota | B4: =Assunzioni!B36
A5: Capex conversione ambulatorio (pilota, lean) | B5: =Assunzioni!B37
A6: Acconti/opzioni su 2 LOI aggiuntive | B6: =Assunzioni!B39
A7: Working capital + costi centrali di partenza | B7: =B10-B4-B5-B6 | D7: residuo del seed
A8: Totale impieghi | B8: =B4+B5+B6+B7
A9: Fonti e verifica
A10: Seed disponibile | B10: =Assunzioni!B29
A11: Fabbisogno 1 pilota completo (closing + capex) | B11: =B4+B5
A12: Residuo dopo il pilota (per LOI + WC) | B12: =B10-B11
A13: Fabbisogno per convertire PIENAMENTE i 3 (Series A) | B13: =3*(Assunzioni!B7*0.65+Assunzioni!B8)
A14: Lettura onesta: €500k converte 1 ambulatorio PILOTA e blinda 3 LOI (margine sottile). La conversione piena dei 3 e' la Series A (~€1,6M). Per un pilota comodo servirebbero ~€600-700k.

Sheet Gruppo_Returns
A1: Gruppo — P&L a 5 anni e ritorni
B3: Anno 1 | C3: Anno 2 | D3: Anno 3 | E3: Anno 4 | F3: Anno 5
A4: Centri medicalizzati (cumulati) | B4: =Assunzioni!B15 | C4: =Assunzioni!B16 | D4: =Assunzioni!B17 | E4: =Assunzioni!B18 | F4: =Assunzioni!B19
A5: Ricavi gruppo | B5: =B4*Assunzioni!B9*Assunzioni!B12 | C5: =C4*Assunzioni!B9*Assunzioni!B12 | D5: =D4*Assunzioni!B9*Assunzioni!B12 | E5: =E4*Assunzioni!B9*Assunzioni!B12 | F5: =F4*Assunzioni!B9*Assunzioni!B12
A6: EBITDA sedi | B6: =B5*Assunzioni!B10 | C6: =C5*Assunzioni!B10 | D6: =D5*Assunzioni!B10 | E6: =E5*Assunzioni!B10 | F6: =F5*Assunzioni!B10
A7: Costo piattaforma centrale | B7: =-Assunzioni!B22 | C7: =-Assunzioni!B23 | D7: =-Assunzioni!B24 | E7: =-Assunzioni!B25 | F7: =-Assunzioni!B26
A8: EBITDA gruppo | B8: =B6+B7 | C8: =C6+C7 | D8: =D6+D7 | E8: =E6+E7 | F8: =F6+F7
A9: Margine EBITDA gruppo | B9: =IFERROR(B8/B5,0) | C9: =IFERROR(C8/C5,0) | D9: =IFERROR(D8/D5,0) | E9: =IFERROR(E8/E5,0) | F9: =IFERROR(F8/F5,0)
A11: EXIT (Anno 5)
A12: Enterprise Value all'exit (EBITDA A5 x multiplo) | B12: =F8*Assunzioni!B11
A14: CAP TABLE E RITORNI
B15: % post-seed | C15: % post-scala | D15: Valore all'exit | E15: MOIC
A16: Investitore seed (€500k) | B16: =Assunzioni!B29/Assunzioni!B30 | C16: =B16*(1-Assunzioni!B31/Assunzioni!B32-Assunzioni!B33) | D16: =C16*B12 | E16: =D16/Assunzioni!B29
A17: Investitore round di scala | C17: =Assunzioni!B31/Assunzioni!B32 | D17: =C17*B12 | E17: =D17/Assunzioni!B31
A18: Pool ESOP (management + COO) | C18: =Assunzioni!B33 | D18: =C18*B12
A19: Fondatori (Luca, Diana, Marcello) | B19: =1-B16 | C19: =1-C16-C17-C18 | D19: =C19*B12
A20: Totale (check = 100%) | C20: =C16+C17+C18+C19
A22: Nota: valutazioni post-money e ESOP sono ipotesi (celle blu in Assunzioni). Il ritorno dei fondatori
A23: e' al lordo della ripartizione interna (Luca 59,4 / Diana 22 / COO 12 / Marcello 6,6, rapporto 9:1).
